qtstrap/__init__.py
qtstrap/base_application.py
qtstrap/base_window.py
qtstrap/options.py
qtstrap/qt.py
qtstrap/settings.py
qtstrap/experimental/__init__.py
qtstrap/experimental/bindings/bind.py
qtstrap/experimental/bindings/bind_widgets.py
qtstrap/extras/__init__.py
qtstrap/extras/code_editor/__init__.py
qtstrap/extras/code_editor/code_editor.py
qtstrap/extras/code_editor/code_line.py
qtstrap/extras/code_editor/highlighters/__init__.py
qtstrap/extras/code_editor/highlighters/python.py
qtstrap/extras/command_palette/__init__.py
qtstrap/extras/command_palette/command_palette.py
qtstrap/extras/devtools/__init__.py
qtstrap/extras/devtools/inspector.py
qtstrap/extras/devtools/repl.py
qtstrap/extras/devtools/scene_tree.py
qtstrap/extras/devtools/style_editor.py
qtstrap/extras/log_monitor/__init__.py
qtstrap/extras/log_monitor/log_database_handler.py
qtstrap/extras/log_monitor/log_filter_controls.py
qtstrap/extras/log_monitor/log_profile.py
qtstrap/extras/log_monitor/log_table_view.py
qtstrap/extras/log_monitor/log_widget.py
qtstrap/extras/settings_model/__init__.py
qtstrap/extras/settings_model/settings_model.py
qtstrap/extras/style/__init__.py
qtstrap/extras/style/colors.py
qtstrap/extras/style/dark_palette.py
qtstrap/extras/style/themes.py
qtstrap/optional/__init__.py
qtstrap/template/.gitignore
qtstrap/template/Makefile
qtstrap/template/requirements.txt
qtstrap/template/app/main.py
qtstrap/template/app/resources/application.ico
qtstrap/template/app/resources/icon.svg
qtstrap/template/scripts/bundle.spec
qtstrap/template/scripts/installer.iss
qtstrap/template/scripts/onefile.spec
qtstrap/utils/__init__.py
qtstrap/utils/adapter.py
qtstrap/utils/call_later.py
qtstrap/utils/classprop.py
qtstrap/utils/defer.py
qtstrap/utils/drag_and_drop.py
qtstrap/utils/get_ip.py
qtstrap/utils/signals.py
qtstrap/utils/singleton.py
qtstrap/utils/string_builder.py
qtstrap/utils/timestamp.py
qtstrap/utils/trace.py
qtstrap/utils/utils.py
qtstrap/widgets/__init__.py
qtstrap-0.7.1.dist-info/LICENSE
qtstrap-0.7.1.dist-info/METADATA
qtstrap-0.7.1.dist-info/WHEEL
qtstrap-0.7.1.dist-info/top_level.txt
qtstrap-0.7.1.dist-info/RECORD
