Metadata-Version: 2.1
Name: qtstrap
Version: 0.7.1
Summary: Like Bootstrap, but qt-er.
Author-email: David Kincaid <daelonsuzuka@gmail.com>
License: MIT License
Project-URL: Homepage, https://github.com/qtstrap/qtstrap
Project-URL: Documentation, https://docs.qtstrap.dev
Project-URL: Repository, https://github.com/qtstrap/qtstrap
Project-URL: Issues, https://github.com/qtstrap/qtstrap/issues
Classifier: Development Status :: 4 - Beta
Classifier: Intended Audience :: Developers
Classifier: Topic :: Software Development :: Widget Sets
Classifier: Topic :: Software Development :: Build Tools
Classifier: Operating System :: OS Independent
Classifier: License :: OSI Approved :: MIT License
Classifier: Programming Language :: Python :: 3
Classifier: Programming Language :: Python :: 3.9
Classifier: Programming Language :: Python :: 3.10
Classifier: Programming Language :: Python :: 3.11
Classifier: Programming Language :: Python :: 3.12
Classifier: Programming Language :: Python :: 3.13
Requires-Python: >=3.9
License-File: LICENSE
Requires-Dist: qtpy>=2.4.1
Requires-Dist: appdirs>=1.4.4
Requires-Dist: qtawesome>=1.3.1
Requires-Dist: pydantic>=2.9.0
Requires-Dist: pydantic-settings>=2.7.0
